<?xml version="1.0" encoding="utf-8"?>
<Deployment xmlns="http://schemas.microsoft.com/windowsphone/2014/deployment" AppPlatformVersion="8.1">
  <DefaultLanguage xmlns="" code="en-US" />
  <App xmlns="" ProductID="{323ed406-9da6-41fc-916c-95f11ea2a3e1}" Title="Hacker News" RuntimeType="Silverlight" Version="1.2.5.0" Genre="apps.normal" Author="Matt McCormick" Description="Hacker News for Windows Phone" Publisher="Matt McCormick" PublisherID="{4af0212d-81cc-440a-88ac-8704dff68d18}">
    <IconPath IsRelative="true" IsResource="false">Assets\ApplicationIcon.png</IconPath>
    <Capabilities>
      <Capability Name="ID_CAP_NETWORKING" />
      <Capability Name="ID_CAP_WEBBROWSERCOMPONENT" />
    </Capabilities>
    <Tasks>
      <DefaultTask Name="_default" NavigationPage="MainPage.xaml" />
      <ExtendedTask Name="BackgroundTask">
        <BackgroundServiceAgent Specifier="ScheduledTaskAgent" Name="HackerNews.Agent" Source="HackerNews.Agent" Type="HackerNews.Agent.ScheduledAgent" />
      </ExtendedTask>
    </Tasks>
    <Tokens>
      <PrimaryToken TokenID="HackerNewsToken" TaskName="_default">
        <TemplateIconic>
          <SmallImageURI IsRelative="true" IsResource="false">Assets\Tiles\SmallIconImage.png</SmallImageURI>
          <IconImageURI IsRelative="true" IsResource="false">Assets\Tiles\IconImage.png</IconImageURI>
          <Title>Hacker News</Title>
          <BackgroundColor>#FFFF6600</BackgroundColor>
          <HasLarge>True</HasLarge>
        </TemplateIconic>
      </PrimaryToken>
    </Tokens>
    <ScreenResolutions>
      <ScreenResolution Name="ID_RESOLUTION_WVGA" />
      <ScreenResolution Name="ID_RESOLUTION_WXGA" />
      <ScreenResolution Name="ID_RESOLUTION_HD720P" />
    </ScreenResolutions>
  </App>
</Deployment>